{
  "menu": [
    {
      "img": "img/tabs/vegy.jpg",
      "altimg": "vegy",
      "title": "Меню 'Фитнес'",
      "descr": "Меню 'Фитнес' - это новый подход к приготовлению блюд: больше свежих овощей и фруктов. Продукт активных и здоровых людей. Это абсолютно новый продукт с оптимальной ценой и высоким качеством!",
      "price": 9
    },
    {
      "img": "img/tabs/post.jpg",
      "altimg": "post",
      "title": "Меню 'Постное'",
      "descr": "Меню 'Постное' - это тщательный подбор ингредиентов: полное отсутствие продуктов животного происхождения, молоко из миндаля, овса, кокоса или гречки, правильное количество белков за счет тофу и импортных вегетарианских стейков.",
      "price": 14
    },
    {
      "img": "img/tabs/elite.jpg",
      "altimg": "elite",
      "title": "Меню 'Премиум'",
      "descr": "В меню 'Премиум' мы используем не только красивый дизайн упаковки, но и качественное исполнение блюд. Красная рыба, морепродукты, фрукты - ресторанное меню без похода в ресторан!",
      "price": 21
    }
  ],
  "requests": [
    {
      "name": "fjknlm,",
      "phone": "2345678",
      "id": 1
    },
    {
      "name": "serdfgchvjbnlk",
      "phone": "234567890-",
      "id": 2
    },
    {
      "name": "bvdhsgb",
      "phone": "nvfjsrh",
      "id": 3
    },
    {
      "name": "dcfgv",
      "phone": "bhjm ",
      "id": 4
    },
    {
      "name": "ewr",
      "phone": "eagyu",
      "id": 5
    },
    {
      "name": "ertyuio",
      "phone": "1234567",
      "id": 6
    },
    {
      "name": "twefgcv sdv",
      "phone": "345678",
      "id": 7
    },
    {
      "name": "jigf",
      "phone": "23456789",
      "id": 8
    },
    {
      "name": "qwertj",
      "phone": "23456",
      "id": 9
    },
    {
      "name": "dfgbnm",
      "phone": "56789",
      "id": 10
    },
    {
      "name": "cmvbkjnfg",
      "phone": "436457",
      "id": 11
    },
    {
      "name": "sndjg",
      "phone": "374856",
      "id": 12
    },
    {
      "name": "vmdfbh",
      "phone": "213671t8",
      "id": 13
    },
    {
      "name": "hdbyfrv",
      "phone": "625372i",
      "id": 14
    },
    {
      "name": "yut567bh",
      "phone": "776890",
      "id": 15
    },
    {
      "name": "bxdsjhbf",
      "phone": "62145",
      "id": 16
    },
    {
      "name": "`nbdjshfj",
      "phone": "8375",
      "id": 17
    },
    {
      "name": "eifjn ",
      "phone": "3206",
      "id": 18
    },
    {
      "name": "njcdksbg",
      "phone": "7562q",
      "id": 19
    },
    {
      "name": "bvnmy",
      "phone": "234657",
      "id": 20
    },
    {
      "name": "msakflabw",
      "phone": "45867",
      "id": 21
    }
  ]
}